{
  "$schema": "https://mintlify.com/docs.json",
  "name": "Seguros NAG",
  "theme": "almond",
  "colors": {
    "primary": "#061e3d",
    "light": "#7c8c9a",
    "dark": "#bcc4cd"
  },
  "favicon": "https://media.brand.dev/fedac39b-e64e-4900-b649-508900f30f83.svg",
  "logo": {
    "light": "https://media.brand.dev/771b85b6-80a6-4855-9a2a-b708701d2d71.svg",
    "dark": "https://media.brand.dev/771b85b6-80a6-4855-9a2a-b708701d2d71.svg"
  },
  "navbar": {
    "primary": {
      "type": "github",
      "href": "https://github.com/p0nkx/seguros-web"
    }
  },
  "footer": {
    "socials": {
      "github": "https://github.com/p0nkx/seguros-web"
    }
  },
  "navigation": {
    "groups": [
      {
        "group": "Get Started",
        "pages": [
          "introduction",
          "quickstart"
        ]
      },
      {
        "group": "Components",
        "pages": [
          "components/header",
          "components/footer",
          "components/cotizacion-form",
          "components/whatsapp-button",
          "components/scroll-to-top"
        ]
      },
      {
        "group": "Configuration",
        "pages": [
          "configuration/seguros-config",
          "configuration/validators",
          "configuration/styling"
        ]
      },
      {
        "group": "Pages",
        "pages": [
          "pages/home",
          "pages/cotizacion",
          "pages/login"
        ]
      },
      {
        "group": "API",
        "pages": [
          "api/enviar-email"
        ]
      }
    ]
  }
}
